guarana/__init__.py
guarana/__main__.py
guarana/config.py
guarana/comandos/__init__.py
guarana/comandos/atualizar.py
guarana/comandos/criar_css.py
guarana/comandos/helpers.py
guarana/comandos/instalar.py
guarana/comandos/js.py
guarana/comandos/observar_minificacao.py
guarana/comandos/rodar.py
guarana/comandos/snippets.py
guarana/doc/atualizar_doc_base.py
guarana/doc/tabelas/__init__.py
guarana/doc/tabelas/classes.py
guarana/doc/tabelas/propriedades.py
guarana/origem/rodar.py
guarana/origem/app/__init__.py
guarana/origem/app/config.py
guarana/origem/app/routes.py
guarana_aag-0.2.0.dist-info/LICENSE
guarana_aag-0.2.0.dist-info/METADATA
guarana_aag-0.2.0.dist-info/WHEEL
guarana_aag-0.2.0.dist-info/top_level.txt
guarana_aag-0.2.0.dist-info/RECORD
