Metadata-Version: 2.1
Name: guarana-aag
Version: 0.2.0
Summary: Framework para uso no Python
Author-email: Alessandro Guarita <alessandro.guarita@gmail.com>
License: MIT
Classifier: Programming Language :: Python :: 3
Classifier: License :: OSI Approved :: MIT License
Classifier: Operating System :: OS Independent
Requires-Python: >=3.13.0
License-File: LICENSE
Requires-Dist: colorama
Requires-Dist: flask
Requires-Dist: markdown
